UtilsRPANAGEM/__init__.py
UtilsRPANAGEM/conexao_banco.py
UtilsRPANAGEM/enviar_email.py
UtilsRPANAGEM/manipula_datahora.py
UtilsRPANAGEM/manipula_diretorios_arquivos.py
UtilsRPANAGEM/manipula_sap.py
utilsrpanagem-1.0.8.dist-info/METADATA
utilsrpanagem-1.0.8.dist-info/WHEEL
utilsrpanagem-1.0.8.dist-info/licenses/LICENSE
utilsrpanagem-1.0.8.dist-info/RECORD
