Metadata-Version: 2.4
Name: UtilsRPANAGEM
Version: 1.0.8
Summary: Conjunto de funcionalidades uteis para o UtilsRPANAGEM.
Project-URL: Homepage, https://github.com/eduardathayse/modulo_rpa_nagem
Project-URL: Bug Tracker, https://github.com/eduardathayse/modulo_rpa_nagem
Author-email: Eduarda Lima <eduarda.lima@nagem.com.br>
License: Copyright (c) 2025 UtilsRPANAGEM
License-File: LICENSE
Classifier: Operating System :: Microsoft :: Windows
Classifier: Programming Language :: Python :: 3
Requires-Python: >=3.12
Requires-Dist: bs4<0.0.3,>=0.0.2
Requires-Dist: chardet<6.0.0,>=5.2.0
Requires-Dist: openpyxl<4.0.0,>=3.1.5
Requires-Dist: pandas<3.0.0,>=2.3.0
Requires-Dist: psutil<8.0.0,>=7.0.0
Requires-Dist: pyodbc<6.0.0,>=5.2.0
Requires-Dist: pywin32<311,>=310
Requires-Dist: requests<3.0.0,>=2.32.4
Requires-Dist: tqdm<5.0.0,>=4.67.1
